selinux/__init__.py
selinux_please_lie_to_me-1.0.1.dist-info/COPYING
selinux_please_lie_to_me-1.0.1.dist-info/METADATA
selinux_please_lie_to_me-1.0.1.dist-info/WHEEL
selinux_please_lie_to_me-1.0.1.dist-info/top_level.txt
selinux_please_lie_to_me-1.0.1.dist-info/RECORD
