Metadata-Version: 2.1
Name: selinux-please-lie-to-me
Version: 1.0.1
Summary: Fake selinux module that always says SELinux is off
Home-page: https://github.com/goneri/selinux_please_lie_to_me
Author: Gonéri Le Bouder
Author-email: goneri@lebouder.net
License: MIT
Project-URL: Bug Tracker, https://github.com/goneri/selinux_please_lie_to_me/issues
Keywords: selinux
Platform: any
Classifier: Intended Audience :: Developers
Classifier: License :: OSI Approved :: MIT License
Classifier: Operating System :: OS Independent
Classifier: Programming Language :: Python
Classifier: Programming Language :: Python :: 2.7
Classifier: Programming Language :: Python :: 3.4
Classifier: Programming Language :: Python :: 3.5
Classifier: Programming Language :: Python :: 3.6
Classifier: Programming Language :: Python :: 3.7
Classifier: Programming Language :: Python :: 3.8
Classifier: Programming Language :: Python :: 3.9
Classifier: Topic :: Software Development :: Libraries :: Python Modules
Requires-Python: >=2.7
